csreuter/__init__.py
csreuter/cli.py
csreuter-0.1.0.dist-info/LICENSE
csreuter-0.1.0.dist-info/METADATA
csreuter-0.1.0.dist-info/WHEEL
csreuter-0.1.0.dist-info/entry_points.txt
csreuter-0.1.0.dist-info/top_level.txt
csreuter-0.1.0.dist-info/RECORD
